eefolium/__init__.py
eefolium/common.py
eefolium/conversion.py
eefolium/eefolium.py
eefolium-0.2.0.dist-info/LICENSE
eefolium-0.2.0.dist-info/METADATA
eefolium-0.2.0.dist-info/WHEEL
eefolium-0.2.0.dist-info/dependency_links.txt
eefolium-0.2.0.dist-info/top_level.txt
eefolium-0.2.0.dist-info/RECORD
