Metadata-Version: 2.1
Name: eefolium
Version: 0.2.0
Summary: A lightweight Python package for interactive mapping with Google Earth Engine and folium
Home-page: https://github.com/giswqs/eefolium
Author: Qiusheng Wu
Author-email: giswqs@gmail.com
License: MIT license
Keywords: eefolium
Classifier: Development Status :: 2 - Pre-Alpha
Classifier: Intended Audience :: Developers
Classifier: License :: OSI Approved :: MIT License
Classifier: Natural Language :: English
Classifier: Programming Language :: Python :: 3
Classifier: Programming Language :: Python :: 3.8
Classifier: Programming Language :: Python :: 3.9
Classifier: Programming Language :: Python :: 3.10
Classifier: Programming Language :: Python :: 3.11
Requires-Python: >=3.5
License-File: LICENSE
Requires-Dist: earthengine-api
Requires-Dist: folium >=0.11.0
